codenerix_pos/__init__.py
codenerix_pos/admin.py
codenerix_pos/apps.py
codenerix_pos/authbackend.py
codenerix_pos/consumers.py
codenerix_pos/forms.py
codenerix_pos/helpers.py
codenerix_pos/models.py
codenerix_pos/routing.py
codenerix_pos/settings.py
codenerix_pos/urls.py
codenerix_pos/views.py
codenerix_pos/management/__init__.py
codenerix_pos/management/__pycache__/__init__.cpython-35.pyc
codenerix_pos/management/__pycache__/__init__.cpython-39.pyc
codenerix_pos/management/commands/__init__.py
codenerix_pos/management/commands/pos_reset.py
codenerix_pos/management/commands/.ropeproject/config.py
codenerix_pos/management/commands/.ropeproject/globalnames
codenerix_pos/management/commands/.ropeproject/history
codenerix_pos/management/commands/.ropeproject/objectdb
codenerix_pos/management/commands/__pycache__/__init__.cpython-39.pyc
codenerix_pos/management/commands/__pycache__/pos_reset.cpython-39.pyc
codenerix_pos/migrations/0001_initial.py
codenerix_pos/migrations/0002_auto_20180227_0912.py
codenerix_pos/migrations/0003_pos_print_unpaid.py
codenerix_pos/migrations/__init__.py
codenerix_pos/migrations/__pycache__/0001_initial.cpython-310.pyc
codenerix_pos/migrations/__pycache__/0001_initial.cpython-35.pyc
codenerix_pos/migrations/__pycache__/0001_initial.cpython-39.pyc
codenerix_pos/migrations/__pycache__/0002_auto_20180227_0912.cpython-310.pyc
codenerix_pos/migrations/__pycache__/0002_auto_20180227_0912.cpython-35.pyc
codenerix_pos/migrations/__pycache__/0002_auto_20180227_0912.cpython-39.pyc
codenerix_pos/migrations/__pycache__/0003_pos_print_unpaid.cpython-310.pyc
codenerix_pos/migrations/__pycache__/0003_pos_print_unpaid.cpython-35.pyc
codenerix_pos/migrations/__pycache__/0003_pos_print_unpaid.cpython-39.pyc
codenerix_pos/migrations/__pycache__/__init__.cpython-310.pyc
codenerix_pos/migrations/__pycache__/__init__.cpython-35.pyc
codenerix_pos/migrations/__pycache__/__init__.cpython-39.pyc
codenerix_pos/static/codenerix_pos/poshardwares_rows.html
django_codenerix_pos-4.0.4.dist-info/LICENSE
django_codenerix_pos-4.0.4.dist-info/METADATA
django_codenerix_pos-4.0.4.dist-info/WHEEL
django_codenerix_pos-4.0.4.dist-info/top_level.txt
django_codenerix_pos-4.0.4.dist-info/RECORD
