Metadata-Version: 2.1
Name: django-codenerix-pos
Version: 4.0.4
Summary: Codenerix Products is a module that enables CODENERIX to set Point of Services on serveral platforms in a general manner.
Home-page: https://github.com/codenerix/django-codenerix-pos
Author: Juan Miguel Taboada Godoy <juanmi@juanmitaboada.com>, Juan Soler Ruiz <soleronline@gmail.com>
License: Apache License Version 2.0
Keywords: django,codenerix,management,erp,pos
Platform: OS Independent
Classifier: Environment :: Web Environment
Classifier: Framework :: Django
Classifier: Framework :: Django :: 1.8
Classifier: Framework :: Django :: 1.9
Classifier: Framework :: Django :: 1.10
Classifier: Intended Audience :: Developers
Classifier: License :: Other/Proprietary License
Classifier: Operating System :: OS Independent
Classifier: Programming Language :: Python
Classifier: Programming Language :: Python :: 3.5
Classifier: Programming Language :: Python :: 3.6
Classifier: Programming Language :: Python :: 3.7
Classifier: Programming Language :: Python :: 3.8
Classifier: Programming Language :: Python :: 3.9
Classifier: Topic :: Internet :: WWW/HTTP
Classifier: Topic :: Internet :: WWW/HTTP :: Dynamic Content
License-File: LICENSE
Requires-Dist: Twisted[http2,tls]
Requires-Dist: asgi-redis
Requires-Dist: celery
Requires-Dist: channels
Requires-Dist: channels-redis
Requires-Dist: codenerix-lib
Requires-Dist: django-codenerix
Requires-Dist: django-codenerix-corporate
Requires-Dist: django-codenerix-invoicing
Requires-Dist: django-codenerix-payments
Requires-Dist: service-identity
